djcopybook/__init__.py
djcopybook/fixedwidth/__init__.py
djcopybook/fixedwidth/fields.py
djcopybook/fixedwidth/tests/__init__.py
djcopybook/fixedwidth/tests/record_helper.py
djcopybook/fixedwidth/tests/test_records.py
djcopybook/fixedwidth/tests/fields/__init__.py
djcopybook/fixedwidth/tests/fields/test_boolean_field.py
djcopybook/fixedwidth/tests/fields/test_date_field.py
djcopybook/fixedwidth/tests/fields/test_datetime_field.py
djcopybook/fixedwidth/tests/fields/test_decimal_field.py
djcopybook/fixedwidth/tests/fields/test_fixed_width_field.py
djcopybook/fixedwidth/tests/fields/test_fragment_field.py
djcopybook/fixedwidth/tests/fields/test_implied_decimal_field.py
djcopybook/fixedwidth/tests/fields/test_integer_field.py
djcopybook/fixedwidth/tests/fields/test_list_field.py
djcopybook/fixedwidth/tests/fields/test_new_line_field.py
djcopybook/fixedwidth/tests/fields/test_null_boolean_field.py
djcopybook/fixedwidth/tests/fields/test_padding.py
djcopybook/fixedwidth/tests/fields/test_postal_code_field.py
djcopybook/fixedwidth/tests/fields/test_signed_implied_decimal_field.py
djcopybook/fixedwidth/tests/fields/test_string_field.py
django_copybook-1.3.2.dist-info/LICENSE
django_copybook-1.3.2.dist-info/METADATA
django_copybook-1.3.2.dist-info/WHEEL
django_copybook-1.3.2.dist-info/top_level.txt
django_copybook-1.3.2.dist-info/RECORD
